cenotes/__init__.py
cenotes/api.py
cenotes/cli.py
cenotes/config_backend.py
cenotes/controllers.py
cenotes/controllers_errors.py
cenotes/helpers.py
cenotes/models.py
cenotes-0.9.0.dist-info/METADATA
cenotes-0.9.0.dist-info/RECORD
cenotes-0.9.0.dist-info/WHEEL
cenotes-0.9.0.dist-info/entry_points.txt
cenotes-0.9.0.dist-info/top_level.txt
tests/__init__.py
tests/conftest.py
tests/test_api.py
tests/test_controllers.py
tests/test_errors.py
tests/test_models.py
