Metadata-Version: 2.1
Name: cenotes
Version: 0.9.0
Summary: Cryptographical Expendable Notes
Home-page: https://github.com/cenotes/cenotes
Author: John Paraskevopoulos
Author-email: ioparaskev@gmail.comm
License: GNU General Public License v3
Keywords: cenotes
Platform: UNKNOWN
Classifier: Development Status :: 4 - Beta
Classifier: Intended Audience :: Developers
Classifier: License :: OSI Approved :: GNU General Public License v3 (GPLv3)
Classifier: Natural Language :: English
Classifier: Programming Language :: Python
Classifier: Programming Language :: Python :: 3
Classifier: Programming Language :: Python :: 3.5
Classifier: Programming Language :: Python :: 3.6
Classifier: Programming Language :: Python :: 3.7
Requires-Python: >=3.4
Requires-Dist: flask (>=0.12.2)
Requires-Dist: pynacl (>=1.2.0)
Requires-Dist: cenotes-lib (>=0.2.0)
Requires-Dist: flask-sqlalchemy (==2.3.2)
Requires-Dist: flask-migrate (==2.1.1)
Requires-Dist: flask-script (==2.0.6)
Requires-Dist: python-dateutil (>=2.6.1)
Requires-Dist: pyyaml (>=4.2b1)
